LICENSE
MANIFEST.in
README.rst
pycgminer.py
setup.py
pycgminer.egg-info/PKG-INFO
pycgminer.egg-info/SOURCES.txt
pycgminer.egg-info/dependency_links.txt
pycgminer.egg-info/top_level.txt