Metadata-Version: 1.1
Name: pycgminer
Version: 0.1.1
Summary: Cgminer RPC API wrapper.
Home-page: https://github.com/tsileo/pycgminer
Author: Thomas Sileo
Author-email: thomas.sileo@gmail.com
License: MIT
Keywords: cgminer
Platform: UNKNOWN
Classifier: Development Status :: 4 - Beta
Classifier: Intended Audience :: Developers
Classifier: License :: OSI Approved :: GNU General Public License v2 (GPLv2)
Classifier: Programming Language :: Python
